xiuxian_rift/__init__.py
xiuxian_rift/jsondata.py
xiuxian_rift/old_rift_info.py
xiuxian_rift/riftconfig.py
xiuxian_rift/riftmake.py
xiuxian_rift-0.30.dist-info/METADATA
xiuxian_rift-0.30.dist-info/WHEEL
xiuxian_rift-0.30.dist-info/top_level.txt
xiuxian_rift-0.30.dist-info/RECORD
