Metadata-Version: 2.1
Name: xiuxian_rift
Version: 0.30
Summary: 修仙数据包
Home-page: https://github.com/luoyefufeng/nonebot_plugin_simulator_xiuxian
Author: 甘城菜月
Author-email: 2859385794@qq.com
License: MIT license
Platform: all
